[
    {
        "id": 0,
        "gamename": "Terraria",
        "game": {
            "versions": [
                {
                    "version": "1.4.4.9.v4",
                    "downloadlink": "https://www.mediafire.com/file/z537rywpsprfgba/",
                    "dlc": "False",
                    "gamelength": "503.71 MB (COMPACTED)",
                    "dateadded": "30/01/2025"
                }
            ]
        }
    },
    {
        "id": 1,
        "gamename": "Subnautica",
        "game": {
            "versions": [
                {
                    "version": "67383",
                    "downloadlink": "https://drive.google.com/uc?id=1EHesVYWpAMeI4EjTGKOibWMDXdUnZzEY&export=download",
                    "dlc": "False",
                    "gamelength": "3.65 GB (COMPACTED)",
                    "dateadded": "30/01/2025"
                },
                {
                    "version": "71668",
                    "downloadlink": "https://www.mediafire.com/file/f893xhzl0ynn1g0/",
                    "dlc": "False",
                    "gamelength": "3.32 GB (COMPACTED)",
                    "dateadded": "30/01/2025"
                },
                {
                    "version": "02/07/2024 | 75268",
                    "downloadlink": "https://www.mediafire.com/file/9bk9jsex23z9xqb/",
                    "dlc": "False",
                    "gamelength": "6.62 GB",
                    "dateadded": "30/01/2025"
                }
            ]
        }
    },
    {
        "id": 2,
        "gamename": "Factorio",
        "game": {
            "versions": [
                {
                    "version": "2.0.20",
                    "downloadlink": "https://www.mediafire.com/file/1a3sfg77ptjbx0x/",
                    "dlc": "False",
                    "gamelength": "4.68 GB",
                    "dateadded": "30/01/2025"
                },
                {
                    "version": "2.0.20 Space Age",
                    "downloadlink": "https://www.mediafire.com/file/dletsk7z81znyug/",
                    "dlc": "True",
                    "gamelength": "5 GB",
                    "dateadded": "30/01/2025"
                }
            ]
        }
    },
    {
        "id": 3,
        "gamename": "60 Seconds Reatomized",
        "game": {
            "versions": [
                {
                    "version": "1.1.5.32",
                    "downloadlink": "https://www.mediafire.com/file/tn266egbmdfh40w/",
                    "dlc": "False",
                    "gamelength": "2.51 GB",
                    "dateadded": "30/01/2025"
                }
            ]
        }
    },
    {
        "id": 4,
        "gamename": "Papers, Please",
        "game": {
            "versions": [
                {
                    "version": "1.4.11.124",
                    "downloadlink": "https://www.mediafire.com/file/xt0o4818naxgcsp/",
                    "dlc": "False",
                    "gamelength": "94.4 MB",
                    "dateadded": "30/01/2025"
                }
            ]
        }
    },
    {
        "id": 5,
        "gamename": "Rimworld",
        "game": {
            "versions": [
                {
                    "version": "1.5.4048",
                    "downloadlink": "https://www.mediafire.com/file/1hz9bfvtg8ol3u0/",
                    "dlc": "True",
                    "gamelength": "653 MB",
                    "dateadded": "30/01/2025"
                }
            ]
        }
    },
    {
        "id": 6,
        "gamename": "Oxygen Not Included",
        "game": {
            "versions": [
                {
                    "version": "596100",
                    "downloadlink": "https://www.mediafire.com/file/8po0nbgoqystqng/",
                    "dlc": "True",
                    "gamelength": "2,85 GB",
                    "dateadded": "30/01/2025"
                },
                {
                    "version": "651155",
                    "downloadlink": "https://www.mediafire.com/file/lqjfoapyjfsvsov/",
                    "dlc": "True",
                    "gamelength": "3.00 GB",
                    "dateadded": "30/01/2025"
                }
            ]
        }
    }
]